odoo/addons/fieldservice_account/README.rst
odoo/addons/fieldservice_account/__init__.py
odoo/addons/fieldservice_account/__manifest__.py
odoo/addons/fieldservice_account/i18n/de.po
odoo/addons/fieldservice_account/i18n/es.po
odoo/addons/fieldservice_account/i18n/es_CL.po
odoo/addons/fieldservice_account/i18n/fieldservice_account.pot
odoo/addons/fieldservice_account/i18n/pt_BR.po
odoo/addons/fieldservice_account/migrations/12.0.3.0.0/post-migration.py
odoo/addons/fieldservice_account/models/__init__.py
odoo/addons/fieldservice_account/models/account_invoice.py
odoo/addons/fieldservice_account/models/account_invoice_line.py
odoo/addons/fieldservice_account/models/fsm_order.py
odoo/addons/fieldservice_account/readme/CONFIGURE.rst
odoo/addons/fieldservice_account/readme/CONTRIBUTORS.rst
odoo/addons/fieldservice_account/readme/CREDITS.rst
odoo/addons/fieldservice_account/readme/DESCRIPTION.rst
odoo/addons/fieldservice_account/readme/INSTALL.rst
odoo/addons/fieldservice_account/readme/USAGE.rst
odoo/addons/fieldservice_account/security/ir.model.access.csv
odoo/addons/fieldservice_account/static/description/icon.png
odoo/addons/fieldservice_account/static/description/index.html
odoo/addons/fieldservice_account/tests/__init__.py
odoo/addons/fieldservice_account/tests/test_fsm_account.py
odoo/addons/fieldservice_account/views/account_invoice.xml
odoo/addons/fieldservice_account/views/fsm_order.xml
odoo12_addon_fieldservice_account-12.0.3.1.1.dist-info/METADATA
odoo12_addon_fieldservice_account-12.0.3.1.1.dist-info/WHEEL
odoo12_addon_fieldservice_account-12.0.3.1.1.dist-info/top_level.txt
odoo12_addon_fieldservice_account-12.0.3.1.1.dist-info/RECORD
